yt_iframe/__init__.py
yt_iframe/yt.py
yt_iframe-0.1.dist-info/METADATA
yt_iframe-0.1.dist-info/WHEEL
yt_iframe-0.1.dist-info/top_level.txt
yt_iframe-0.1.dist-info/RECORD
