Metadata-Version: 2.1
Name: yt-iframe
Version: 0.1
Summary: YouTube video iframe generator
Home-page: http://github.com/robbyb97/yt-iframe-python
Author: Robby Bergers
Author-email: bergersr@my.easternct.edu
License: MIT
Platform: UNKNOWN
